pycounts_jy2024/__init__.py
pycounts_jy2024/plotting.py
pycounts_jy2024/pycounts_jy2024.py
pycounts_jy2024-0.2.0.dist-info/LICENSE
pycounts_jy2024-0.2.0.dist-info/METADATA
pycounts_jy2024-0.2.0.dist-info/WHEEL
pycounts_jy2024-0.2.0.dist-info/RECORD
